{"@context":"https://linked.art/ns/v1/linked-art.json","id":"https://www.moma.org/data/Activity/364","type":"Activity","_label":"Useful Objects","classified_as":[{"id":"http://vocab.getty.edu/aat/300054766","type":"Type","_label":"Exhibiting"}],"identified_by":[{"type":"Name","classified_as":[{"id":"http://vocab.getty.edu/aat/300404670","type":"Type","_label":"Primary Name"}],"content":"Useful Objects"}],"timespan":{"type":"TimeSpan","begin_of_the_begin":"1945-11-21T00:00:00Z","end_of_the_end":"1946-01-06T23:59:59Z"},"took_place_at":[{"type":"Place","_label":"MoMA","classified_as":[{"id":"http://vocab.getty.edu/aat/300260522","type":"Type","_label":"exhibition building spaces"}],"defined_by":"POINT(40.7623 -73.97749)"},{"type":"Place","_label":"11 West 53rd St.","classified_as":[{"id":"http://vocab.getty.edu/aat/300419273","type":"Type","_label":"thoroughfare names"}]}],"carried_out_by":[{"id":"https://www.moma.org/data/Group/inst3","type":"Group","_label":"The Museum of Modern Art","identified_by":[{"type":"Name","content":"The Museum of Modern Art"}],"equivalent":[{"id":"http://vocab.getty.edu/ulan/500303609","type":"Group","_label":"The Museum of Modern Art - ULAN"},{"id":"http://www.wikidata.org/entity/Q188740","type":"Group","_label":"The Museum of Modern Art - Wikidata"}]},{"id":"https://www.moma.org/data/Person/29162","type":"Person","_label":"Susanne Wasson-Tucker","identified_by":[{"type":"Name","content":"Susanne Wasson-Tucker"},{"type":"Identifier","content":"9493","attributed_by":[{"type":"AttributeAssignment","carried_out_by":[{"id":"https://www.moma.org/data/Group/inst2","type":"Group","_label":"The Metropolitan Museum of Art","identified_by":[{"type":"Name","content":"The Metropolitan Museum of Art"}],"equivalent":[{"id":"http://vocab.getty.edu/ulan/500309699","type":"Group","_label":"The Metropolitan Museum of Art - ULAN"},{"id":"http://www.wikidata.org/entity/Q160236","type":"Group","_label":"The Metropolitan Museum of Art - Wikidata"}]}]}]}]}],"subject_of":[{"type":"LinguisticObject","digitally_carried_by":[{"type":"DigitalObject","classified_as":[{"id":"http://vocab.getty.edu/aat/300264578","type":"Type","_label":"Web Page"}],"access_point":[{"id":"http://www.moma.org/calendar/exhibitions/2731","type":"DigitalObject"}]}]}],"influenced_by":[{"id":"https://www.moma.org/data/Group/8829","type":"Group","_label":"Swift & Anderson, Inc., Boston, MA","classified_as":[{"id":"http://vocab.getty.edu/aat/300107956","type":"Type","_label":"American","classified_as":[{"id":"http://vocab.getty.edu/aat/300379842","type":"Type","_label":"Nationality"}]}],"identified_by":[{"type":"Name","content":"Swift & Anderson, Inc., Boston, MA"},{"type":"Identifier","content":"9832","attributed_by":[{"type":"AttributeAssignment","carried_out_by":[{"id":"https://www.moma.org/data/Group/inst2","type":"Group","_label":"The Metropolitan Museum of Art"}]}]}]},{"id":"https://www.moma.org/data/Group/8668","type":"Group","_label":"Artek-Pascoe, Inc., New York, NY","identified_by":[{"type":"Name","content":"Artek-Pascoe, Inc., New York, NY"},{"type":"Identifier","content":"9502","attributed_by":[{"type":"AttributeAssignment","carried_out_by":[{"id":"https://www.moma.org/data/Group/inst2","type":"Group","_label":"The Metropolitan Museum of Art"}]}]}]},{"id":"https://www.moma.org/data/Group/8732","type":"Group","_label":"A.H. Heisey & Co., Newark, Ohio","classified_as":[{"id":"http://vocab.getty.edu/aat/300107956","type":"Type","_label":"American"}],"identified_by":[{"type":"Name","content":"A.H. Heisey & Co., Newark, Ohio"},{"type":"Identifier","content":"9622","attributed_by":[{"type":"AttributeAssignment","carried_out_by":[{"id":"https://www.moma.org/data/Group/inst2","type":"Group","_label":"The Metropolitan Museum of Art"}]}]}],"formed_by":{"type":"Formation","timespan":{"type":"TimeSpan","identified_by":[{"type":"Name","classified_as":[{"id":"http://vocab.getty.edu/aat/300404669","type":"Type","_label":"Display Title"}],"content":"1896"}],"begin_of_the_begin":"1896-01-01T00:00:00Z","end_of_the_end":"1896-12-31T23:59:59Z"}}},{"id":"https://www.moma.org/data/Group/8660","type":"Group","_label":"Cambridge Glass Company, Cambridge, OH","classified_as":[{"id":"http://vocab.getty.edu/aat/300107956","type":"Type","_label":"American"}],"identified_by":[{"type":"Name","content":"Cambridge Glass Company, Cambridge, OH"},{"type":"Identifier","content":"9487","attributed_by":[{"type":"AttributeAssignment","carried_out_by":[{"id":"https://www.moma.org/data/Group/inst2","type":"Group","_label":"The Metropolitan Museum of Art"}]}]}],"formed_by":{"type":"Formation","timespan":{"type":"TimeSpan","identified_by":[{"type":"Name","classified_as":[{"id":"http://vocab.getty.edu/aat/300404669","type":"Type","_label":"Display Title"}],"content":"1873"}],"begin_of_the_begin":"1873-01-01T00:00:00Z","end_of_the_end":"1873-12-31T23:59:59Z"}},"dissolved_by":{"type":"Dissolution","timespan":{"type":"TimeSpan","identified_by":[{"type":"Name","classified_as":[{"id":"http://vocab.getty.edu/aat/300404669","type":"Type","_label":"Display Title"}],"content":"1958"}],"begin_of_the_begin":"1958-01-01T00:00:00Z","end_of_the_end":"1958-12-31T23:59:59Z"}}},{"id":"https://www.moma.org/data/Group/8695","type":"Group","_label":"Imperial Glass Corp., Bellaire, OH","classified_as":[{"id":"http://vocab.getty.edu/aat/300107956","type":"Type","_label":"American"}],"identified_by":[{"type":"Name","content":"Imperial Glass Corp., Bellaire, OH"},{"type":"Identifier","content":"9562","attributed_by":[{"type":"AttributeAssignment","carried_out_by":[{"id":"https://www.moma.org/data/Group/inst2","type":"Group","_label":"The Metropolitan Museum of Art"}]}]}]},{"id":"https://www.moma.org/data/Group/8601","type":"Group","_label":"The Watertown Manufacturing Co., Watertown, CT","classified_as":[{"id":"http://vocab.getty.edu/aat/300107956","type":"Type","_label":"American"}],"identified_by":[{"type":"Name","content":"The Watertown Manufacturing Co., Watertown, CT"},{"type":"Identifier","content":"9392","attributed_by":[{"type":"AttributeAssignment","carried_out_by":[{"id":"https://www.moma.org/data/Group/inst2","type":"Group","_label":"The Metropolitan Museum of Art"}]}]}]},{"id":"https://www.moma.org/data/Group/8472","type":"Group","_label":"American Optical Corp., Southbridge, MA","classified_as":[{"id":"http://vocab.getty.edu/aat/300107956","type":"Type","_label":"American"}],"identified_by":[{"type":"Name","content":"American Optical Corp., Southbridge, MA"},{"type":"Identifier","content":"9179","attributed_by":[{"type":"AttributeAssignment","carried_out_by":[{"id":"https://www.moma.org/data/Group/inst2","type":"Group","_label":"The Metropolitan Museum of Art"}]}]}],"formed_by":{"type":"Formation","timespan":{"type":"TimeSpan","identified_by":[{"type":"Name","classified_as":[{"id":"http://vocab.getty.edu/aat/300404669","type":"Type","_label":"Display Title"}],"content":"1850"}],"begin_of_the_begin":"1850-01-01T00:00:00Z","end_of_the_end":"1850-12-31T23:59:59Z"}}},{"id":"https://www.moma.org/data/Group/9475","type":"Group","_label":"Guilford Art Company","identified_by":[{"type":"Name","content":"Guilford Art Company"},{"type":"Identifier","content":"11098","attributed_by":[{"type":"AttributeAssignment","carried_out_by":[{"id":"https://www.moma.org/data/Group/inst2","type":"Group","_label":"The Metropolitan Museum of Art"}]}]}]},{"id":"https://www.moma.org/data/Group/8527","type":"Group","_label":"Ekco Products Co., Chicago, IL","classified_as":[{"id":"http://vocab.getty.edu/aat/300107956","type":"Type","_label":"American"}],"identified_by":[{"type":"Name","content":"Ekco Products Co., Chicago, IL"},{"type":"Identifier","content":"9259","attributed_by":[{"type":"AttributeAssignment","carried_out_by":[{"id":"https://www.moma.org/data/Group/inst2","type":"Group","_label":"The Metropolitan Museum of Art"}]}]}],"equivalent":[{"id":"http://viaf.org/viaf/Q5323238","type":"Group","_label":"Ekco Products Co., Chicago, IL - VIAF"}],"formed_by":{"type":"Formation","timespan":{"type":"TimeSpan","identified_by":[{"type":"Name","classified_as":[{"id":"http://vocab.getty.edu/aat/300404669","type":"Type","_label":"Display Title"}],"content":"1888"}],"begin_of_the_begin":"1888-01-01T00:00:00Z","end_of_the_end":"1888-12-31T23:59:59Z"}}},{"id":"https://www.moma.org/data/Group/23081","type":"Group","_label":"Reynolds Metals Company","identified_by":[{"type":"Name","content":"Reynolds Metals Company"},{"type":"Identifier","content":"38325","attributed_by":[{"type":"AttributeAssignment","carried_out_by":[{"id":"https://www.moma.org/data/Group/inst2","type":"Group","_label":"The Metropolitan Museum of Art"}]}]}],"equivalent":[{"id":"http://viaf.org/viaf/Q3428914","type":"Group","_label":"Reynolds Metals Company - VIAF"}]},{"id":"https://www.moma.org/data/Group/8701","type":"Group","_label":"Landers, Frary & Clark, New Britain, CT","classified_as":[{"id":"http://vocab.getty.edu/aat/300107956","type":"Type","_label":"American"}],"identified_by":[{"type":"Name","content":"Landers, Frary & Clark, New Britain, CT"},{"type":"Identifier","content":"9575","attributed_by":[{"type":"AttributeAssignment","carried_out_by":[{"id":"https://www.moma.org/data/Group/inst2","type":"Group","_label":"The Metropolitan Museum of Art"}]}]}]},{"id":"https://www.moma.org/data/Group/8827","type":"Group","_label":"Almo, New York","classified_as":[{"id":"http://vocab.getty.edu/aat/300107956","type":"Type","_label":"American"}],"identified_by":[{"type":"Name","content":"Almo, New York"},{"type":"Identifier","content":"9822","attributed_by":[{"type":"AttributeAssignment","carried_out_by":[{"id":"https://www.moma.org/data/Group/inst2","type":"Group","_label":"The Metropolitan Museum of Art"}]}]}]},{"id":"https://www.moma.org/data/Group/8780","type":"Group","_label":"Lalance & Grosjean Mfg. Co., Woodhaven, NY","classified_as":[{"id":"http://vocab.getty.edu/aat/300107956","type":"Type","_label":"American"}],"identified_by":[{"type":"Name","content":"Lalance & Grosjean Mfg. Co., Woodhaven, NY"},{"type":"Identifier","content":"9724","attributed_by":[{"type":"AttributeAssignment","carried_out_by":[{"id":"https://www.moma.org/data/Group/inst2","type":"Group","_label":"The Metropolitan Museum of Art"}]}]}]},{"id":"https://www.moma.org/data/Person/20721","type":"Person","_label":"William J. Russell","classified_as":[{"id":"http://vocab.getty.edu/aat/300107956","type":"Type","_label":"American"}],"identified_by":[{"type":"Name","content":"William J. Russell"},{"type":"Identifier","content":"34310","attributed_by":[{"type":"AttributeAssignment","carried_out_by":[{"id":"https://www.moma.org/data/Group/inst2","type":"Group","_label":"The Metropolitan Museum of Art"}]}]}],"referred_to_by":[{"type":"LinguisticObject","classified_as":[{"id":"http://vocab.getty.edu/aat/300435422","type":"Type","_label":"Biography Statement","classified_as":[{"id":"http://vocab.getty.edu/aat/300418049","type":"Type","_label":"Brief Text"}]}],"content":"Male"}]},{"id":"https://www.moma.org/data/Group/8823","type":"Group","_label":"Carrollton Metal Products Company, Carrollton, OH","identified_by":[{"type":"Name","content":"Carrollton Metal Products Company, Carrollton, OH"},{"type":"Identifier","content":"9800","attributed_by":[{"type":"AttributeAssignment","carried_out_by":[{"id":"https://www.moma.org/data/Group/inst2","type":"Group","_label":"The Metropolitan Museum of Art"}]}]}]},{"id":"https://www.moma.org/data/Group/8726","type":"Group","_label":"General Lighting Co., Brooklyn, NY","identified_by":[{"type":"Name","content":"General Lighting Co., Brooklyn, NY"},{"type":"Identifier","content":"9608","attributed_by":[{"type":"AttributeAssignment","carried_out_by":[{"id":"https://www.moma.org/data/Group/inst2","type":"Group","_label":"The Metropolitan Museum of Art"}]}]}]},{"id":"https://www.moma.org/data/Group/29746","type":"Group","_label":"Bachman Bros. Inc.","identified_by":[{"type":"Name","content":"Bachman Bros. Inc."},{"type":"Identifier","content":"65146","attributed_by":[{"type":"AttributeAssignment","carried_out_by":[{"id":"https://www.moma.org/data/Group/inst2","type":"Group","_label":"The Metropolitan Museum of Art"}]}]}]},{"id":"https://www.moma.org/data/Group/28995","type":"Group","_label":"Richards, Boggs and King, Inc.","identified_by":[{"type":"Name","content":"Richards, Boggs and King, Inc."},{"type":"Identifier","content":"66752","attributed_by":[{"type":"AttributeAssignment","carried_out_by":[{"id":"https://www.moma.org/data/Group/inst2","type":"Group","_label":"The Metropolitan Museum of Art"}]}]}]},{"id":"https://www.moma.org/data/Group/29753","type":"Group","_label":"Trippe Mfg. Co.","identified_by":[{"type":"Name","content":"Trippe Mfg. Co."},{"type":"Identifier","content":"62812","attributed_by":[{"type":"AttributeAssignment","carried_out_by":[{"id":"https://www.moma.org/data/Group/inst2","type":"Group","_label":"The Metropolitan Museum of Art"}]}]}]},{"id":"https://www.moma.org/data/Group/29755","type":"Group","_label":"Klein's Gift Shop","identified_by":[{"type":"Name","content":"Klein's Gift Shop"},{"type":"Identifier","content":"62814","attributed_by":[{"type":"AttributeAssignment","carried_out_by":[{"id":"https://www.moma.org/data/Group/inst2","type":"Group","_label":"The Metropolitan Museum of Art"}]}]}]},{"id":"https://www.moma.org/data/Group/29754","type":"Group","_label":"Yorkville Novelty Co.","identified_by":[{"type":"Name","content":"Yorkville Novelty Co."},{"type":"Identifier","content":"62813","attributed_by":[{"type":"AttributeAssignment","carried_out_by":[{"id":"https://www.moma.org/data/Group/inst2","type":"Group","_label":"The Metropolitan Museum of Art"}]}]}]},{"id":"https://www.moma.org/data/Person/29106","type":"Person","_label":"Mario H.G. Torres","identified_by":[{"type":"Name","content":"Mario H.G. Torres"},{"type":"Identifier","content":"64690","attributed_by":[{"type":"AttributeAssignment","carried_out_by":[{"id":"https://www.moma.org/data/Group/inst2","type":"Group","_label":"The Metropolitan Museum of Art"}]}]}]},{"id":"https://www.moma.org/data/Group/29721","type":"Group","_label":"Venus Corp.","identified_by":[{"type":"Name","content":"Venus Corp."},{"type":"Identifier","content":"65121","attributed_by":[{"type":"AttributeAssignment","carried_out_by":[{"id":"https://www.moma.org/data/Group/inst2","type":"Group","_label":"The Metropolitan Museum of Art"}]}]}]},{"id":"https://www.moma.org/data/Group/27811","type":"Group","_label":"Alfred Dunhill of London, Inc.","identified_by":[{"type":"Name","content":"Alfred Dunhill of London, Inc."},{"type":"Identifier","content":"66362","attributed_by":[{"type":"AttributeAssignment","carried_out_by":[{"id":"https://www.moma.org/data/Group/inst2","type":"Group","_label":"The Metropolitan Museum of Art"}]}]}]},{"id":"https://www.moma.org/data/Group/29748","type":"Group","_label":"Livingston Plastics Corp.","identified_by":[{"type":"Name","content":"Livingston Plastics Corp."},{"type":"Identifier","content":"65148","attributed_by":[{"type":"AttributeAssignment","carried_out_by":[{"id":"https://www.moma.org/data/Group/inst2","type":"Group","_label":"The Metropolitan Museum of Art"}]}]}]},{"id":"https://www.moma.org/data/Group/29684","type":"Group","_label":"Precision Products Co.","identified_by":[{"type":"Name","content":"Precision Products Co."},{"type":"Identifier","content":"62152","attributed_by":[{"type":"AttributeAssignment","carried_out_by":[{"id":"https://www.moma.org/data/Group/inst2","type":"Group","_label":"The Metropolitan Museum of Art"}]}]}]},{"id":"https://www.moma.org/data/Group/29752","type":"Group","_label":"Zippo Mfg. Co.","identified_by":[{"type":"Name","content":"Zippo Mfg. Co."},{"type":"Identifier","content":"62811","attributed_by":[{"type":"AttributeAssignment","carried_out_by":[{"id":"https://www.moma.org/data/Group/inst2","type":"Group","_label":"The Metropolitan Museum of Art"}]}]}]},{"id":"https://www.moma.org/data/Group/29705","type":"Group","_label":"Kampa Mfg. Co.","identified_by":[{"type":"Name","content":"Kampa Mfg. Co."},{"type":"Identifier","content":"65105","attributed_by":[{"type":"AttributeAssignment","carried_out_by":[{"id":"https://www.moma.org/data/Group/inst2","type":"Group","_label":"The Metropolitan Museum of Art"}]}]}]},{"id":"https://www.moma.org/data/Group/29744","type":"Group","_label":"Baby World Co.","identified_by":[{"type":"Name","content":"Baby World Co."},{"type":"Identifier","content":"65144","attributed_by":[{"type":"AttributeAssignment","carried_out_by":[{"id":"https://www.moma.org/data/Group/inst2","type":"Group","_label":"The Metropolitan Museum of Art"}]}]}]},{"id":"https://www.moma.org/data/Group/29751","type":"Group","_label":"B.W. Photo Utilities","identified_by":[{"type":"Name","content":"B.W. Photo Utilities"},{"type":"Identifier","content":"65151","attributed_by":[{"type":"AttributeAssignment","carried_out_by":[{"id":"https://www.moma.org/data/Group/inst2","type":"Group","_label":"The Metropolitan Museum of Art"}]}]}]},{"id":"https://www.moma.org/data/Group/29747","type":"Group","_label":"Frank Paper Products","identified_by":[{"type":"Name","content":"Frank Paper Products"},{"type":"Identifier","content":"65147","attributed_by":[{"type":"AttributeAssignment","carried_out_by":[{"id":"https://www.moma.org/data/Group/inst2","type":"Group","_label":"The Metropolitan Museum of Art"}]}]}]},{"id":"https://www.moma.org/data/Group/29749","type":"Group","_label":"Plastic Molded Products, Inc.","identified_by":[{"type":"Name","content":"Plastic Molded Products, Inc."},{"type":"Identifier","content":"65149","attributed_by":[{"type":"AttributeAssignment","carried_out_by":[{"id":"https://www.moma.org/data/Group/inst2","type":"Group","_label":"The Metropolitan Museum of Art"}]}]}]},{"id":"https://www.moma.org/data/Group/29750","type":"Group","_label":"Gudebrod Bros., Silk Co., Inc.","identified_by":[{"type":"Name","content":"Gudebrod Bros., Silk Co., Inc."},{"type":"Identifier","content":"65150","attributed_by":[{"type":"AttributeAssignment","carried_out_by":[{"id":"https://www.moma.org/data/Group/inst2","type":"Group","_label":"The Metropolitan Museum of Art"}]}]}]},{"id":"https://www.moma.org/data/Group/29745","type":"Group","_label":"Just Plastics, Inc.","identified_by":[{"type":"Name","content":"Just Plastics, Inc."},{"type":"Identifier","content":"65145","attributed_by":[{"type":"AttributeAssignment","carried_out_by":[{"id":"https://www.moma.org/data/Group/inst2","type":"Group","_label":"The Metropolitan Museum of Art"}]}]}]},{"id":"https://www.moma.org/data/Person/33","type":"Person","_label":"Alvar Aalto","identified_by":[{"type":"Name","content":"Alvar Aalto"},{"type":"Identifier","content":"34","attributed_by":[{"type":"AttributeAssignment","carried_out_by":[{"id":"https://www.moma.org/data/Group/inst2","type":"Group","_label":"The Metropolitan Museum of Art"}]}]}],"referred_to_by":[{"type":"LinguisticObject","classified_as":[{"id":"http://vocab.getty.edu/aat/300435422","type":"Type","_label":"Biography Statement"}],"content":"Male"}],"born":{"type":"Birth","timespan":{"type":"TimeSpan","identified_by":[{"type":"Name","classified_as":[{"id":"http://vocab.getty.edu/aat/300404669","type":"Type","_label":"Display Title"}],"content":"1898"}],"begin_of_the_begin":"1898-01-01T00:00:00Z","end_of_the_end":"1898-12-31T23:59:59Z"}},"died":{"type":"Death","timespan":{"type":"TimeSpan","identified_by":[{"type":"Name","classified_as":[{"id":"http://vocab.getty.edu/aat/300404669","type":"Type","_label":"Display Title"}],"content":"1976"}],"begin_of_the_begin":"1976-01-01T00:00:00Z","end_of_the_end":"1976-12-31T23:59:59Z"}},"equivalent":[{"id":"http://www.wikidata.org/entity/500002617","type":"Person","_label":"Alvar Aalto - Wikidata"},{"id":"http://viaf.org/viaf/Q82840","type":"Person","_label":"Alvar Aalto - VIAF"}]}]}